esi_requests/__init__.py
esi_requests/__version__.py
esi_requests/api.py
esi_requests/checker.py
esi_requests/exceptions.py
esi_requests/metadata.py
esi_requests/models.py
esi_requests/parser.py
esi_requests/sessions.py
esi_requests/utils.py
esi_requests/data/__init__.py
esi_requests/data/cache.py
esi_requests/data/db.py
esi_requests/data/etag_cache.py
esi_requests/data/schema.yml
esi_requests/data/utils.py
esi_requests/log/__init__.py
esi_requests/log/log.py
esi_requests/sso/application.json
esi_requests/sso/application.py
esi_requests/sso/esi_oauth_native.py
esi_requests/sso/refresh_token.py
esi_requests/sso/shared_flow.py
esi_requests/sso/token.py
esi_requests/sso/utils.py
esi_requests/sso/validate_jwt.py
esi_requests-0.0.1.10.dist-info/LICENSE
esi_requests-0.0.1.10.dist-info/METADATA
esi_requests-0.0.1.10.dist-info/WHEEL
esi_requests-0.0.1.10.dist-info/top_level.txt
esi_requests-0.0.1.10.dist-info/RECORD
