Metadata-Version: 2.1
Name: esi-requests
Version: 0.0.1.10
Summary: A simple library for asynchronous ESI requests
Author-email: Hanbo <hb.evetools@gmail.com>
License: BSD-3-Clause
Keywords: python,esi,eve-online,asyncio
Classifier: Development Status :: 2 - Pre-Alpha
Classifier: Intended Audience :: Developers
Classifier: Programming Language :: Python :: 3
Requires-Python: >=3.7
License-File: LICENSE
Requires-Dist: pandas
Requires-Dist: numpy
Requires-Dist: requests
Requires-Dist: aiohttp
Requires-Dist: python-jose
Requires-Dist: pyperclip
Requires-Dist: pyyaml
Requires-Dist: tqdm >=4.62.0
Requires-Dist: concurrent-log-handler ; sys_platform == "win32"
